MongoDBLibrary/__init__.py
MongoDBLibrary/mongo_connection_manager.py
MongoDBLibrary/mongoquery.py
MongoDBLibrary/version.py
robotframework_mongodb_library-3.2.dist-info/LICENSE
robotframework_mongodb_library-3.2.dist-info/METADATA
robotframework_mongodb_library-3.2.dist-info/WHEEL
robotframework_mongodb_library-3.2.dist-info/top_level.txt
robotframework_mongodb_library-3.2.dist-info/RECORD
